figshare_driver/__init__.py
figshare_driver/retrieve.py
figshare_driver-0.0.4.dist-info/LICENSE
figshare_driver-0.0.4.dist-info/METADATA
figshare_driver-0.0.4.dist-info/WHEEL
figshare_driver-0.0.4.dist-info/top_level.txt
figshare_driver-0.0.4.dist-info/RECORD
