Metadata-Version: 2.1
Name: figshare_driver
Version: 0.0.4
Summary: Functions required by the figshare-driver
Author-email: Cristian Garcia <cristian.garcia@ubiquitypress.com>
Classifier: Programming Language :: Python :: 3
Classifier: License :: OSI Approved :: MIT License
Classifier: Operating System :: OS Independent
Requires-Python: >=3.10
License-File: LICENSE
